sequence_classifiers/__init__.py
sequence_classifiers/cnn.py
sklearn_sequence_classifiers-0.2.dist-info/DESCRIPTION.rst
sklearn_sequence_classifiers-0.2.dist-info/METADATA
sklearn_sequence_classifiers-0.2.dist-info/RECORD
sklearn_sequence_classifiers-0.2.dist-info/WHEEL
sklearn_sequence_classifiers-0.2.dist-info/metadata.json
sklearn_sequence_classifiers-0.2.dist-info/top_level.txt
tests/__init__.py
tests/test_cnn.py
